{
  "projects": [
    { "id": 1, "title": "Project 001","desc": "What does Lorem Ipsum mean? Derived from Latin do…", "thumbnail": "https://images.unsplash.com/photo-1599303737038-03f59a722b55?ixlib=rb-1.2.1&ixid=eyJhcHBfaWQiOjEyMDd9&auto=format&fit=crop&w=100&q=80" },
    { "id": 2, "title": "Project 001","desc": "What does Lorem Ipsum mean? Derived from Latin do…", "thumbnail": "https://images.unsplash.com/photo-1599303737038-03f59a722b55?ixlib=rb-1.2.1&ixid=eyJhcHBfaWQiOjEyMDd9&auto=format&fit=crop&w=100&q=80" },
    { "id": 3, "title": "Project 001","desc": "What does Lorem Ipsum mean? Derived from Latin do…", "thumbnail": "https://images.unsplash.com/photo-1599303737038-03f59a722b55?ixlib=rb-1.2.1&ixid=eyJhcHBfaWQiOjEyMDd9&auto=format&fit=crop&w=100&q=80" },
    { "id": 4, "title": "Project 001","desc": "What does Lorem Ipsum mean? Derived from Latin do…", "thumbnail": "https://images.unsplash.com/photo-1599303737038-03f59a722b55?ixlib=rb-1.2.1&ixid=eyJhcHBfaWQiOjEyMDd9&auto=format&fit=crop&w=100&q=80" },
    { "id": 5, "title": "Project 001","desc": "What does Lorem Ipsum mean? Derived from Latin do…", "thumbnail": "https://images.unsplash.com/photo-1599303737038-03f59a722b55?ixlib=rb-1.2.1&ixid=eyJhcHBfaWQiOjEyMDd9&auto=format&fit=crop&w=100&q=80" },
    { "id": 6, "title": "Project 001","desc": "What does Lorem Ipsum mean? Derived from Latin do…", "thumbnail": "https://images.unsplash.com/photo-1599303737038-03f59a722b55?ixlib=rb-1.2.1&ixid=eyJhcHBfaWQiOjEyMDd9&auto=format&fit=crop&w=100&q=80" },
    { "id": 7, "title": "Project 001","desc": "What does Lorem Ipsum mean? Derived from Latin do…", "thumbnail": "https://images.unsplash.com/photo-1599303737038-03f59a722b55?ixlib=rb-1.2.1&ixid=eyJhcHBfaWQiOjEyMDd9&auto=format&fit=crop&w=100&q=80" },
    { "id": 8, "title": "Project 001","desc": "What does Lorem Ipsum mean? Derived from Latin do…", "thumbnail": "https://images.unsplash.com/photo-1599303737038-03f59a722b55?ixlib=rb-1.2.1&ixid=eyJhcHBfaWQiOjEyMDd9&auto=format&fit=crop&w=100&q=80" },
    { "id": 9, "title": "Project 001","desc": "What does Lorem Ipsum mean? Derived from Latin do…", "thumbnail": "https://images.unsplash.com/photo-1599303737038-03f59a722b55?ixlib=rb-1.2.1&ixid=eyJhcHBfaWQiOjEyMDd9&auto=format&fit=crop&w=100&q=80" },
    { "id": 10, "title": "Project 001","desc": "What does Lorem Ipsum mean? Derived from Latin do…", "thumbnail": "https://images.unsplash.com/photo-1599303737038-03f59a722b55?ixlib=rb-1.2.1&ixid=eyJhcHBfaWQiOjEyMDd9&auto=format&fit=crop&w=100&q=80" }
  ]
}
